{
  "schemaVersion": "catfish.self-optimization.v1",
  "globalId": "catfish-research",
  "label": "CatfishResearch",
  "worker": {
    "worker_id": "self-optimizer",
    "label": "Self Optimizer",
    "status": "running",
    "queue_name": "self-optimization",
    "active_task_id": "opt-task-module-scout",
    "completed_tasks": 12,
    "last_heartbeat_at": "2026-03-28T10:12:00Z",
    "summary": "Consumes only global experience and routes it into safe self-improvement trials."
  },
  "queue": [
    {
      "task_id": "opt-task-module-scout",
      "queue_name": "self-optimization",
      "scope": "global",
      "status": "running",
      "priority": "high",
      "objective": "Scout stronger implementation support modules after repeated builder usage.",
      "target_kind": "module-scout",
      "source_report_id": "experience:global:global:global:catfish-research",
      "competition_id": "global-scout-implementation",
      "candidate_ids": [
        "candidate:promptfoo",
        "candidate:d2"
      ],
      "created_at": "2026-03-28T10:00:00Z",
      "updated_at": "2026-03-28T10:11:30Z",
      "summary": "Global self-improvement work is isolated from project branch competition.",
      "metadata": {
        "trigger": "module-use:implementation-builder",
        "trigger_count": 5
      }
    }
  ],
  "module_scout_contracts": [
    {
      "contract_id": "scout-contract-implementation",
      "module_id": "scheduler/implementation-builder",
      "module_label": "Implementation Builder",
      "capability": "implementation",
      "search_query": "best autonomous coding evaluation and branch competition repos",
      "allowlist_manifest": "assets/external_repos/catfish_module_scout_manifest.example.json",
      "allowed_source_ids": [
        "promptfoo",
        "d2"
      ],
      "safe_install_modes": [
        "clone-reference",
        "convert-to-skill"
      ],
      "max_candidates": 4,
      "require_explicit_allowlist": true,
      "require_human_review": true,
      "created_at": "2026-03-28T09:58:00Z",
      "summary": "Only allowlisted modules may move from scouting into trial installation."
    }
  ],
  "module_scout_candidates": [
    {
      "candidate_id": "candidate:promptfoo",
      "contract_id": "scout-contract-implementation",
      "source_kind": "repo",
      "source_id": "promptfoo",
      "title": "promptfoo",
      "capability": "implementation",
      "source_url": "https://github.com/promptfoo/promptfoo",
      "install_policy": "clone-reference",
      "conversion_target": "skill",
      "competition_id": "global-scout-implementation",
      "score_entry_id": "candidate:promptfoo",
      "metadata": {
        "novelty_score": 0.78,
        "quality_score": 0.91,
        "fit_score": 0.88,
        "operational_score": 0.73,
        "updated_at": "2026-03-28T10:10:00Z"
      },
      "summary": "Best current candidate for turning branch evals into a reusable Catfish skill."
    },
    {
      "candidate_id": "candidate:d2",
      "contract_id": "scout-contract-implementation",
      "source_kind": "repo",
      "source_id": "d2",
      "title": "D2",
      "capability": "architecture-visualization",
      "source_url": "https://github.com/terrastruct/d2",
      "install_policy": "clone-reference",
      "competition_id": "global-scout-implementation",
      "score_entry_id": "candidate:d2",
      "metadata": {
        "novelty_score": 0.62,
        "quality_score": 0.84,
        "fit_score": 0.63,
        "operational_score": 0.82,
        "updated_at": "2026-03-28T10:09:00Z"
      },
      "summary": "Useful support module but weaker fit than the eval harness path."
    }
  ],
  "experience_artifacts": [
    {
      "artifact_id": "global-worker-cycle-20260328",
      "scope": "global",
      "level_kind": "worker",
      "subject_id": "self-optimizer",
      "subject_label": "Self Optimizer",
      "report_kind": "optimization-cycle",
      "direct_score": 0.82,
      "sample_count": 2,
      "hierarchy_path": [
        "global:catfish-research",
        "worker:self-optimizer"
      ],
      "updated_at": "2026-03-28T10:12:00Z",
      "summary": "Global worker is continuously consuming aggregate experience without polluting project state."
    }
  ]
}
